{"nodes": [{"id": "appbuild_AppBuildScript", "label": "App Module Build Script", "file_type": "code", "source_file": "app/build.gradle.kts", "source_location": null, "source_url": null, "captured_at": null, "author": null, "contributor": null}], "edges": [{"source": "appbuild_AppBuildScript", "target": "mainactivity_MainActivity", "relation": "conceptually_related_to", "confidence": "INFERRED", "confidence_score": 0.8, "source_file": "app/build.gradle.kts", "source_location": "line 10", "weight": 1.0}], "hyperedges": []}